lobster/__init__.py
lobster/common/__init__.py
lobster/common/errors.py
lobster/common/exceptions.py
lobster/common/file_collector.py
lobster/common/file_tag_generator.py
lobster/common/io.py
lobster/common/items.py
lobster/common/level_definition.py
lobster/common/lexer.py
lobster/common/location.py
lobster/common/meta_data_tool_base.py
lobster/common/multi_file_input_config.py
lobster/common/multi_file_input_tool.py
lobster/common/parser.py
lobster/common/report.py
lobster/common/tool.py
lobster/common/version.py
lobster/htmldoc/__init__.py
lobster/htmldoc/assets.py
lobster/htmldoc/htmldoc.py
lobster/tools/__init__.py
lobster/tools/codebeamer/__init__.py
lobster/tools/codebeamer/bearer_auth.py
lobster/tools/codebeamer/codebeamer.py
lobster/tools/codebeamer/config.py
lobster/tools/codebeamer/exceptions.py
lobster/tools/core/__init__.py
lobster/tools/core/ci_report/__init__.py
lobster/tools/core/ci_report/ci_report.py
lobster/tools/core/html_report/__init__.py
lobster/tools/core/html_report/html_report.py
lobster/tools/core/html_report/html_report_css.py
lobster/tools/core/html_report/html_report_js.py
lobster/tools/core/online_report/__init__.py
lobster/tools/core/online_report/online_report.py
lobster/tools/core/online_report/path_to_url_converter.py
lobster/tools/core/online_report_nogit/__init__.py
lobster/tools/core/online_report_nogit/online_report_nogit.py
lobster/tools/core/report/__init__.py
lobster/tools/core/report/report.py
lobster/tools/cpp/__init__.py
lobster/tools/cpp/cpp.py
lobster/tools/cpp/implementation_builder.py
lobster/tools/cpptest/__init__.py
lobster/tools/cpptest/constants.py
lobster/tools/cpptest/cpptest.py
lobster/tools/cpptest/requirements_parser.py
lobster/tools/cpptest/testcase.py
lobster/tools/gtest/__init__.py
lobster/tools/gtest/gtest.py
lobster/tools/json/__init__.py
lobster/tools/json/json.py
lobster/tools/pkg/__init__.py
lobster/tools/pkg/pkg.py
lobster/tools/python/__init__.py
lobster/tools/python/python.py
bmw_lobster_monolithic-1.0.2.dist-info/METADATA
bmw_lobster_monolithic-1.0.2.dist-info/WHEEL
bmw_lobster_monolithic-1.0.2.dist-info/entry_points.txt
bmw_lobster_monolithic-1.0.2.dist-info/top_level.txt
bmw_lobster_monolithic-1.0.2.dist-info/RECORD
